yandex_tank_api/__init__.py
yandex_tank_api/common.py
yandex_tank_api/manager.py
yandex_tank_api/webserver.py
yandex_tank_api/worker.py
yandex_tank_api/config/00-tank-api-defaults.ini
yandex_tank_api/config/99-tank-api-override.ini
yandex_tank_api/static/favicon.ico
yandex_tank_api/static/css/bootstrap-theme.css
yandex_tank_api/static/css/bootstrap-theme.min.css
yandex_tank_api/static/css/bootstrap.css
yandex_tank_api/static/css/bootstrap.min.css
yandex_tank_api/static/css/custom.css
yandex_tank_api/static/fonts/glyphicons-halflings-regular.eot
yandex_tank_api/static/fonts/glyphicons-halflings-regular.svg
yandex_tank_api/static/fonts/glyphicons-halflings-regular.ttf
yandex_tank_api/static/fonts/glyphicons-halflings-regular.woff
yandex_tank_api/static/js/manager.js
yandex_tank_api/static/js/vendor/angular.js
yandex_tank_api/static/js/vendor/angular.min.js
yandex_tank_api/static/js/vendor/bootstrap.js
yandex_tank_api/static/js/vendor/bootstrap.min.js
yandex_tank_api/static/js/vendor/jquery.js
yandex_tank_api/static/js/vendor/jquery.min.js
yandex_tank_api/static/js/vendor/ui-bootstrap-tpls-0.12.0.min.js
yandex_tank_api/static/js/vendor/ui-bootstrap-tpls.js
yandex_tank_api/static/js/vendor/underscore-min.js
yandex_tank_api/static/js/vendor/underscore.js
yandex_tank_api/static/js/vendor/ace/ace.js
yandex_tank_api/static/js/vendor/ace/mode-ini.js
yandex_tank_api/static/js/vendor/ace/ui-ace.js
yandex_tank_api/templates/manager.jade
yandex_tank_api-0.0.11.data/scripts/yandex-tank-api-server
yandex_tank_api-0.0.11.dist-info/DESCRIPTION.rst
yandex_tank_api-0.0.11.dist-info/METADATA
yandex_tank_api-0.0.11.dist-info/metadata.json
yandex_tank_api-0.0.11.dist-info/RECORD
yandex_tank_api-0.0.11.dist-info/top_level.txt
yandex_tank_api-0.0.11.dist-info/WHEEL
