Metadata-Version: 2.0
Name: yandex-tank-api
Version: 0.0.11
Summary: Yandex.Tank HTTP API
Home-page: UNKNOWN
Author: Andrei Sekretenko
Author-email: asekretenko@gmail.com
License: UNKNOWN
Platform: UNKNOWN
Classifier: Development Status :: 2 - Pre-Alpha
Classifier: Intended Audience :: Developers
Requires-Dist: tornado (>=3.1)
Requires-Dist: python-daemon (>=1.5.5)
Requires-Dist: yandextank
